ti_plm/__init__.py
ti_plm/cli.py
ti_plm/display.py
ti_plm/util.py
ti_plm/db/__init__.py
ti_plm/db/p47.json
ti_plm/db/p67.json
ti_plm-1.1.0.dist-info/licenses/LICENSE
ti_plm-1.1.0.dist-info/METADATA
ti_plm-1.1.0.dist-info/WHEEL
ti_plm-1.1.0.dist-info/entry_points.txt
ti_plm-1.1.0.dist-info/top_level.txt
ti_plm-1.1.0.dist-info/RECORD
