Metadata-Version: 2.4
Name: ti-plm
Version: 1.1.0
Summary: Easy TI PLM data formatting and phase processing in Python
Author-email: Sam Martin <martins@ti.com>
License-Expression: MIT
Requires-Python: >=3.10
License-File: LICENSE
Requires-Dist: param<3,>=2
Requires-Dist: numpy<3,>=2
Provides-Extra: dev
Requires-Dist: pytest>=7; extra == "dev"
Requires-Dist: flake8; extra == "dev"
Requires-Dist: build; extra == "dev"
Requires-Dist: twine; extra == "dev"
Requires-Dist: mkdocs; extra == "dev"
Requires-Dist: mkdocs-material; extra == "dev"
Requires-Dist: mkdocs-jupyter; extra == "dev"
Requires-Dist: mkdocs-autorefs; extra == "dev"
Requires-Dist: mkdocs-literate-nav; extra == "dev"
Requires-Dist: mkdocstrings[python]; extra == "dev"
Requires-Dist: markdown-exec[ansi]; extra == "dev"
Provides-Extra: display
Requires-Dist: pygame<3,>=2.6; extra == "display"
Requires-Dist: screeninfo<1,>=0.8; extra == "display"
Requires-Dist: pillow<11,>=10; extra == "display"
Dynamic: license-file
